go/testsettings.py
go/urls.py
go/__init__.py
go/settings.py
go/config.py
go/errors.py
go/base/message_store_client.py
go/base/amqp.py
go/base/admin.py
go/base/middleware.py
go/base/widgets.py
go/base/__init__.py
go/base/utils.py
go/base/views.py
go/base/models.py
go/base/forms.py
go/base/command_utils.py
go/base/context_processors.py
go/base/templatetags/__init__.py
go/base/templatetags/go_tags.py
go/base/tests/test_go_manage_router.py
go/base/tests/test_go_manage_contact_group.py
go/base/tests/test_go_create_user.py
go/base/tests/test_go_assign_tagpool.py
go/base/tests/test_go_send_app_worker_command.py
go/base/tests/test_go_manage_http_api.py
go/base/tests/test_go_account_stats.py
go/base/tests/test_go_setup_env.py
go/base/tests/test_command_utils.py
go/base/tests/__init__.py
go/base/tests/test_go_start_conversation.py
go/base/tests/test_go_manage_routing_table.py
go/base/tests/test_go_manage_account.py
go/base/tests/test_go_manage_message_cache.py
go/base/tests/test_go_import_contacts.py
go/base/tests/test_middleware.py
go/base/tests/test_go_migrate_conversations.py
go/base/tests/helpers.py
go/base/tests/test_go_manage_applications.py
go/base/tests/test_base.py
go/base/tests/test_go_list_accounts.py
go/base/tests/test_go_manage_conversation.py
go/base/tests/test_views.py
go/base/tests/test_go_manage_metrics.py
go/base/tests/test_utils.py
go/base/migrations/0006_auto__add_userorganisation__add_field_userprofile_organisation.py
go/base/migrations/0002_auto__add_contact.py
go/base/migrations/0010_auto__chg_field_userprofile_user.py
go/base/migrations/0012_add_gouser_permissions.py
go/base/migrations/0001_initial.py
go/base/migrations/__init__.py
go/base/migrations/0003_auto.py
go/base/migrations/0011_auto__del_user.py
go/base/migrations/0007_auto__add_field_userprofile_is_admin.py
go/base/migrations/0009_migrate_user_to_gouser.py
go/base/migrations/0008_auto__add_gouser.py
vumi_go-0.5.0.dist-info/RECORD
vumi_go-0.5.0.dist-info/METADATA
vumi_go-0.5.0.dist-info/DESCRIPTION.rst
vumi_go-0.5.0.dist-info/top_level.txt
vumi_go-0.5.0.dist-info/metadata.json
vumi_go-0.5.0.dist-info/WHEEL
