Metadata-Version: 2.0
Name: vumi-go
Version: 0.5.0
Summary: Vumi Go
Home-page: http://github.com/praekelt/vumi-go
Author: Praekelt Foundation
Author-email: dev@praekeltfoundation.org
License: BSD
Platform: UNKNOWN
Classifier: Development Status :: 4 - Beta
Classifier: Environment :: Web Environment
Classifier: Framework :: Django
Classifier: Framework :: Twisted
Classifier: Intended Audience :: Developers
Classifier: License :: OSI Approved :: BSD License
Classifier: Operating System :: POSIX
Classifier: Programming Language :: Python
Classifier: Programming Language :: Python :: 2.6
Classifier: Programming Language :: Python :: 2.7
Classifier: Topic :: Communications
Classifier: Topic :: Internet
Classifier: Topic :: System :: Networking
Requires-Dist: vumi (>=0.5.0)
Requires-Dist: vxpolls
Requires-Dist: vumi-wikipedia
Requires-Dist: Django (==1.5.8)
Requires-Dist: gunicorn (==0.15.0)
Requires-Dist: South (==0.8.2)
Requires-Dist: psycopg2 (==2.4)
Requires-Dist: celery (==3.0.23)
Requires-Dist: django-celery (==3.0.23)
Requires-Dist: django-celery-email
Requires-Dist: Markdown (==2.1.1)
Requires-Dist: django-registration (==1.0)
Requires-Dist: lesscpy (==0.9h)
Requires-Dist: xlrd (==0.8.0)
Requires-Dist: requests (==0.14.2)
Requires-Dist: mock (==1.0.1)
Requires-Dist: raven (>=2.0,<3.0)
Requires-Dist: django-debug-toolbar (==0.9.4)
Requires-Dist: kombu (>=2.5,<3.0)
Requires-Dist: librabbitmq (==1.5.1)
Requires-Dist: hiredis (==0.1.4)
Requires-Dist: django-pipeline (==1.3.6)
Requires-Dist: txpostgres (==1.1.0)
Requires-Dist: django-crispy-forms (==1.4.0)
Requires-Dist: django-loginas (==0.1.3)
